{
    "Problem": [
        {
            "Lower bound": 95.0,
            "Name": "tmpee84by0h",
            "Number of constraints": 2443,
            "Number of nonzeros": 1053481,
            "Number of objectives": 1,
            "Number of variables": 75050,
            "Sense": "minimize",
            "Upper bound": 95.0
        }
    ],
    "Solution": [
        {
            "number of solutions": 0,
            "number of solutions displayed": 0
        }
    ],
    "Solver": [
        {
            "Error rc": 0,
            "Statistics": {
                "Branch and bound": {
                    "Number of bounded subproblems": 0,
                    "Number of created subproblems": 0
                }
            },
            "Status": "ok",
            "Termination condition": "optimal",
            "Termination message": "MIP - Integer optimal solution\\x3a Objective = 9.5000000000e+01",
            "Time": 9.86813998222351,
            "User time": 9.22
        }
    ]
}