{
    "Problem": [
        {
            "Lower bound": 69.0,
            "Name": "tmp3zn99wpy",
            "Number of constraints": 1035,
            "Number of nonzeros": 151827,
            "Number of objectives": 1,
            "Number of variables": 17567,
            "Sense": "minimize",
            "Upper bound": 69.0
        }
    ],
    "Solution": [
        {
            "number of solutions": 0,
            "number of solutions displayed": 0
        }
    ],
    "Solver": [
        {
            "Error rc": 0,
            "Statistics": {
                "Branch and bound": {
                    "Number of bounded subproblems": 0,
                    "Number of created subproblems": 0
                }
            },
            "Status": "ok",
            "Termination condition": "optimal",
            "Termination message": "MIP - Integer optimal solution\\x3a Objective = 6.9000000000e+01",
            "Time": 2.387218952178955,
            "User time": 2.23
        }
    ]
}