{
    "Problem": [
        {
            "Lower bound": 66.0,
            "Name": "tmpd0tmo3ok",
            "Number of constraints": 986,
            "Number of nonzeros": 198127,
            "Number of objectives": 1,
            "Number of variables": 15919,
            "Sense": "minimize",
            "Upper bound": 66.0
        }
    ],
    "Solution": [
        {
            "number of solutions": 0,
            "number of solutions displayed": 0
        }
    ],
    "Solver": [
        {
            "Error rc": 0,
            "Statistics": {
                "Branch and bound": {
                    "Number of bounded subproblems": 0,
                    "Number of created subproblems": 0
                }
            },
            "Status": "ok",
            "Termination condition": "optimal",
            "Termination message": "MIP - Integer optimal solution\\x3a Objective = 6.6000000000e+01",
            "Time": 2.5029189586639404,
            "User time": 2.36
        }
    ]
}