{
    "Problem": [
        {
            "Lower bound": 66.5,
            "Name": "tmpb28fh55i",
            "Number of constraints": 6516,
            "Number of nonzeros": 22210,
            "Number of objectives": 1,
            "Number of variables": 3791,
            "Sense": "minimize",
            "Upper bound": 74.00000000000003
        }
    ],
    "Solution": [
        {
            "number of solutions": 0,
            "number of solutions displayed": 0
        }
    ],
    "Solver": [
        {
            "Error rc": 0,
            "Status": "ok",
            "Termination condition": "maxTimeLimit",
            "Termination message": "MIP - Time limit exceeded, integer feasible\\x3a Objective = 7.4000000000e+01",
            "Time": 600.1155602931976,
            "User time": 600.01
        }
    ]
}