{
    "Problem": [
        {
            "Lower bound": 54.0,
            "Name": "tmp8roezfva",
            "Number of constraints": 10244,
            "Number of nonzeros": 30718,
            "Number of objectives": 1,
            "Number of variables": 5627,
            "Sense": "minimize",
            "Upper bound": 54.0
        }
    ],
    "Solution": [
        {
            "number of solutions": 0,
            "number of solutions displayed": 0
        }
    ],
    "Solver": [
        {
            "Error rc": 0,
            "Statistics": {
                "Branch and bound": {
                    "Number of bounded subproblems": 2848,
                    "Number of created subproblems": 2848
                }
            },
            "Status": "ok",
            "Termination condition": "optimal",
            "Termination message": "MIP - Integer optimal solution\\x3a Objective = 5.4000000000e+01",
            "Time": 3.675544023513794,
            "User time": 3.6
        }
    ]
}