{
    "Problem": [
        {
            "Lower bound": 80.0,
            "Name": "tmp3jvnk_sd",
            "Number of constraints": 6056,
            "Number of nonzeros": 20457,
            "Number of objectives": 1,
            "Number of variables": 3501,
            "Sense": "minimize",
            "Upper bound": 80.0
        }
    ],
    "Solution": [
        {
            "number of solutions": 0,
            "number of solutions displayed": 0
        }
    ],
    "Solver": [
        {
            "Error rc": 0,
            "Statistics": {
                "Branch and bound": {
                    "Number of bounded subproblems": 3663,
                    "Number of created subproblems": 3663
                }
            },
            "Status": "ok",
            "Termination condition": "optimal",
            "Termination message": "MIP - Integer optimal solution\\x3a Objective = 8.0000000000e+01",
            "Time": 8.813445091247559,
            "User time": 8.76
        }
    ]
}