{
    "Problem": [
        {
            "Lower bound": 55.0,
            "Name": "tmpz__3sv6h",
            "Number of constraints": 1829,
            "Number of nonzeros": 8001,
            "Number of objectives": 1,
            "Number of variables": 985,
            "Sense": "minimize",
            "Upper bound": 55.0
        }
    ],
    "Solution": [
        {
            "number of solutions": 0,
            "number of solutions displayed": 0
        }
    ],
    "Solver": [
        {
            "Error rc": 0,
            "Statistics": {
                "Branch and bound": {
                    "Number of bounded subproblems": 5095,
                    "Number of created subproblems": 5095
                }
            },
            "Status": "ok",
            "Termination condition": "optimal",
            "Termination message": "MIP - Integer optimal solution\\x3a Objective = 5.5000000000e+01",
            "Time": 7.544135093688965,
            "User time": 7.52
        }
    ]
}