{
    "Problem": [
        {
            "Lower bound": 57.0,
            "Name": "tmpkvqw_i5w",
            "Number of constraints": 1491,
            "Number of nonzeros": 4883,
            "Number of objectives": 1,
            "Number of variables": 793,
            "Sense": "minimize",
            "Upper bound": 57.0
        }
    ],
    "Solution": [
        {
            "number of solutions": 0,
            "number of solutions displayed": 0
        }
    ],
    "Solver": [
        {
            "Error rc": 0,
            "Statistics": {
                "Branch and bound": {
                    "Number of bounded subproblems": 151,
                    "Number of created subproblems": 151
                }
            },
            "Status": "ok",
            "Termination condition": "optimal",
            "Termination message": "MIP - Integer optimal solution\\x3a Objective = 5.7000000000e+01",
            "Time": 0.21883583068847656,
            "User time": 0.2
        }
    ]
}