{
    "Problem": [
        {
            "Lower bound": 64.0,
            "Name": "tmpfjsss_ih",
            "Number of constraints": 1503,
            "Number of nonzeros": 6389,
            "Number of objectives": 1,
            "Number of variables": 793,
            "Sense": "minimize",
            "Upper bound": 64.0
        }
    ],
    "Solution": [
        {
            "number of solutions": 0,
            "number of solutions displayed": 0
        }
    ],
    "Solver": [
        {
            "Error rc": 0,
            "Statistics": {
                "Branch and bound": {
                    "Number of bounded subproblems": 1310,
                    "Number of created subproblems": 1310
                }
            },
            "Status": "ok",
            "Termination condition": "optimal",
            "Termination message": "MIP - Integer optimal solution\\x3a Objective = 6.4000000000e+01",
            "Time": 1.7142858505249023,
            "User time": 1.69
        }
    ]
}